mccloud_cli/__init__.py
mccloud_cli/_version.py
mccloud_cli/cli.py
mccloud_cli/jobs.py
mccloud_cli/s3_utils.py
mccloud_cli/urls.py
mccloud_cli-0.0.8.dist-info/LICENSE.txt
mccloud_cli-0.0.8.dist-info/METADATA
mccloud_cli-0.0.8.dist-info/WHEEL
mccloud_cli-0.0.8.dist-info/entry_points.txt
mccloud_cli-0.0.8.dist-info/top_level.txt
mccloud_cli-0.0.8.dist-info/RECORD
